{
  "sharedData": [],
  "collectedData": [
    {
      "data": "Approximate location",
      "optional": true,
      "purpose": "Analytics",
      "type": "Location"
    },
    {
      "data": "Precise location",
      "optional": true,
      "purpose": "App functionality",
      "type": "Location"
    },
    {
      "data": "Email address",
      "optional": true,
      "purpose": "Account management",
      "type": "Personal info"
    },
    {
      "data": "App interactions",
      "optional": true,
      "purpose": "Analytics",
      "type": "App activity"
    },
    {
      "data": "Other actions",
      "optional": true,
      "purpose": "Analytics",
      "type": "App activity"
    },
    {
      "data": "Crash logs",
      "optional": true,
      "purpose": "Analytics",
      "type": "App info and performance"
    },
    {
      "data": "Diagnostics",
      "optional": true,
      "purpose": "Analytics",
      "type": "App info and performance"
    },
    {
      "data": "Other app performance data",
      "optional": true,
      "purpose": "Analytics",
      "type": "App info and performance"
    },
    {
      "data": "Device or other IDs",
      "optional": true,
      "purpose": "Analytics, Account management",
      "type": "Device or other IDs"
    }
  ],
  "securityPractices": [
    {
      "practice": "Data is encrypted in transit",
      "description": "Your data is transferred over a secure connection"
    },
    {
      "practice": "You can request that data be deleted",
      "description": "The developer provides a way for you to request that your data be deleted"
    }
  ],
  "privacyPolicyUrl": "https://www.apple.com/legal/privacy/en-ww/"
}